secretscanner/__init__.py
secretscanner/__main__.py
secretscanner/entropy.py
secretscanner/find.py
secretscanner/gitignore.py
secretscanner/highlighter.py
secretscanner/progress_column_file.py
secretscanner/report.py
secretscanner/scanner.py
secretscanner/secret_info.py
secretscanner/types.py
secretscanner-0.2.1.dist-info/entry_points.txt
secretscanner-0.2.1.dist-info/WHEEL
secretscanner-0.2.1.dist-info/METADATA
secretscanner-0.2.1.dist-info/RECORD
