Metadata-Version: 2.1
Name: secretscanner
Version: 0.2.1
Summary: Scan for secrets within files.
Home-page: https://github.com/sffjunkie/secretscanner
License: Apache-2.0
Author: Simon Kennedy
Author-email: sffjunkie+code@gmail.com
Requires-Python: >=3.10,<4.0
Classifier: License :: OSI Approved :: Apache Software License
Classifier: Programming Language :: Python :: 3
Classifier: Programming Language :: Python :: 3.10
Requires-Dist: click (>=8.1.3,<9.0.0)
Requires-Dist: pathspec (>=0.10.1,<0.11.0)
Requires-Dist: ppuri (==0.3.1)
Requires-Dist: rich (>=12.5.1,<13.0.0)
Project-URL: Repository, https://github.com/sffjunkie/secretscanner
